dosh/__init__.py
dosh/__main__.py
dosh/base_commands.py
dosh/commands.py
dosh/config.py
dosh/environments.py
dosh/external_commands.py
dosh/injections.py
dosh/internal_commands.py
dosh/logger.py
dosh/lua_runtime.py
dosh_cli-0.2.1.dist-info/licenses/LICENSE.md
dosh_cli-0.2.1.dist-info/METADATA
dosh_cli-0.2.1.dist-info/WHEEL
dosh_cli-0.2.1.dist-info/entry_points.txt
dosh_cli-0.2.1.dist-info/top_level.txt
dosh_cli-0.2.1.dist-info/RECORD
