Metadata-Version: 2.4
Name: dosh-cli
Version: 0.2.1
Summary: Shell-independent task management CLI.
License-Expression: MIT
Classifier: Environment :: Console
Classifier: Intended Audience :: Developers
Classifier: Intended Audience :: System Administrators
Classifier: Natural Language :: English
Classifier: Operating System :: MacOS
Classifier: Operating System :: Microsoft
Classifier: Operating System :: POSIX :: Linux
Classifier: Topic :: Software Development :: Build Tools
Requires-Python: >=3.13
License-File: LICENSE.md
Requires-Dist: colorlog>=6.9.0
Requires-Dist: lupa>=2.4
Dynamic: license-file
